AUTHORS
MANIFEST.in
README
requirements.txt
setup.py
lpbm/__init__.py
lpbm/exceptions.py
lpbm/logging.py
lpbm/main.py
lpbm/module_loader.py
lpbm/tools.py
lpbm.egg-info/PKG-INFO
lpbm.egg-info/SOURCES.txt
lpbm.egg-info/dependency_links.txt
lpbm.egg-info/entry_points.txt
lpbm.egg-info/requires.txt
lpbm.egg-info/top_level.txt
lpbm/models/__init__.py
lpbm/models/articles.py
lpbm/models/authors.py
lpbm/models/categories.py
lpbm/models/configmodel.py
lpbm/modules/__init__.py
lpbm/modules/articles.py
lpbm/modules/authors.py
lpbm/modules/categories.py
lpbm/modules/config.py
lpbm/modules/render.py
lpbm/themes/bootstrap/css/bootstrap.min.css
lpbm/themes/bootstrap/css/main.css
lpbm/themes/bootstrap/css/pygments.css
lpbm/themes/bootstrap/fonts/glyphicons-halflings-regular.eot
lpbm/themes/bootstrap/fonts/glyphicons-halflings-regular.svg
lpbm/themes/bootstrap/fonts/glyphicons-halflings-regular.ttf
lpbm/themes/bootstrap/fonts/glyphicons-halflings-regular.woff
lpbm/themes/bootstrap/images/feed-icon-28x28.png
lpbm/themes/bootstrap/images/glyphicons-halflings-white.png
lpbm/themes/bootstrap/images/glyphicons-halflings.png
lpbm/themes/bootstrap/js/bootstrap.min.js
lpbm/themes/bootstrap/js/jquery.min.js
lpbm/themes/bootstrap/js/main.js
lpbm/themes/bootstrap/templates/base.html
lpbm/themes/bootstrap/templates/paginate.html
lpbm/themes/bootstrap/templates/articles/base.html
lpbm/themes/bootstrap/templates/authors/link.html
lpbm/themes/bootstrap/templates/authors/menu_link.html
lpbm/themes/default/css/main.css
lpbm/themes/default/css/main.scss
lpbm/themes/default/css/pygments.css
lpbm/themes/default/images/feed-icon-28x28.png
lpbm/themes/default/templates/base.html
lpbm/themes/default/templates/paginate.html
lpbm/themes/default/templates/articles/base.html
lpbm/themes/default/templates/authors/link.html
lpbm/themes/default/templates/authors/menu_link.html