Metadata-Version: 1.1
Name: lpbm
Version: 2.0.0
Summary: Lightweight personal blog maker
Home-page: http://bitbucket.org/kushou/lpbm
Author: Franck Michea
Author-email: franck.michea@gmail.com
License: BSD
Platform: UNKNOWN
Classifier: Development Status :: 3 - Alpha
Classifier: Environment :: Console
Classifier: Intended Audience :: End Users/Desktop
Classifier: License :: OSI Approved :: BSD License
Classifier: Programming Language :: Python
Classifier: Programming Language :: Python :: 3
